{
  "ReRoutes": [
    {
      "DownstreamPathTemplate": "/api/values",
      "DownstreamScheme": "http",
      "DownstreamHostAndPorts": [
        {
          "Host": "localhost",
         "Port": "80"
        }
      ],
      "UpstreamPathTemplate": "/values",
      "UpstreamHttpMethod": [ "GET" ],
      "AuthenticationOptions": {
        "AuthenticationProviderKey": "TestKey",
        "AllowedScopes": []
      }
    },
    /***********************Starrating Module********************************/
    /************For Add New File screen********************/
    {
      "DownstreamPathTemplate": "/StarratingApi/api/AddFile/Add",
      "DownstreamScheme": "http",
      "DownstreamHostAndPorts": [
        {
          "Host": "localhost",
          "Port": "80"
        }
      ],
      "UpstreamPathTemplate": "/api/AddFile/Add",
      "UpstreamHttpMethod": [ "POST" ],
      "AuthenticationOptions": {
        "AuthenticationProviderKey": "TestKey",
        "AllowedScopes": []
      }
    },
    {
      "DownstreamPathTemplate": "/StarratingApi/api/AddFile/View",
      "DownstreamScheme": "http",
      "DownstreamHostAndPorts": [
        {
          "Host": "localhost",
          "Port": "80"
        }
      ],
      "UpstreamPathTemplate": "/api/AddFile/View",
      "UpstreamHttpMethod": [ "POST" ],
      "AuthenticationOptions": {
        "AuthenticationProviderKey": "TestKey",
        "AllowedScopes": []
      }
    },
    /************For Assessment screen********************/
    {
      "DownstreamPathTemplate": "/StarratingApi/api/Assessment/View",
      "DownstreamScheme": "http",
      "DownstreamHostAndPorts": [
        {
          "Host": "localhost",
          "Port": "80"
        }
      ],
      "UpstreamPathTemplate": "/api/Assessment/View",
      "UpstreamHttpMethod": [ "POST" ],
      "AuthenticationOptions": {
        "AuthenticationProviderKey": "TestKey",
        "AllowedScopes": []
      }
    },
    {
      "DownstreamPathTemplate": "/StarratingApi/api/Assessment/GetStateList",
      "DownstreamScheme": "http",
      "DownstreamHostAndPorts": [
        {
          "Host": "localhost",
          "Port": "80"
        }
      ],
      "UpstreamPathTemplate": "/api/Assessment/GetStateList",
      "UpstreamHttpMethod": [ "POST" ],
      "AuthenticationOptions": {
        "AuthenticationProviderKey": "TestKey",
        "AllowedScopes": []
      }
    },
    {
      "DownstreamPathTemplate": "/StarratingApi/api/Assessment/GetDistrictList",
      "DownstreamScheme": "http",
      "DownstreamHostAndPorts": [
        {
          "Host": "localhost",
          "Port": "80"
        }
      ],
      "UpstreamPathTemplate": "/api/Assessment/GetDistrictList",
      "UpstreamHttpMethod": [ "POST" ],
      "AuthenticationOptions": {
        "AuthenticationProviderKey": "TestKey",
        "AllowedScopes": []
      }
    },
    {
      "DownstreamPathTemplate": "/StarratingApi/api/Assessment/GetTehsilList",
      "DownstreamScheme": "http",
      "DownstreamHostAndPorts": [
        {
          "Host": "localhost",
          "Port": "80"
        }
      ],
      "UpstreamPathTemplate": "/api/Assessment/GetTehsilList",
      "UpstreamHttpMethod": [ "POST" ],
      "AuthenticationOptions": {
        "AuthenticationProviderKey": "TestKey",
        "AllowedScopes": []
      }
    },
    {
      "DownstreamPathTemplate": "/StarratingApi/api/Assessment/GetVillageList",
      "DownstreamScheme": "http",
      "DownstreamHostAndPorts": [
        {
          "Host": "localhost",
          "Port": "80"
        }
      ],
      "UpstreamPathTemplate": "/api/Assessment/GetVillageList",
      "UpstreamHttpMethod": [ "POST" ],
      "AuthenticationOptions": {
        "AuthenticationProviderKey": "TestKey",
        "AllowedScopes": []
      }
    },
    /************For Starrating screen********************/
    {
      "DownstreamPathTemplate": "/StarratingApi/api/Starrating/ViewAssessmentTemplate",
      "DownstreamScheme": "http",
      "DownstreamHostAndPorts": [
        {
          "Host": "localhost",
          "Port": "80"
        }
      ],
      "UpstreamPathTemplate": "/api/Starrating/ViewAssessmentTemplate",
      "UpstreamHttpMethod": [ "POST" ],
      "AuthenticationOptions": {
        "AuthenticationProviderKey": "TestKey",
        "AllowedScopes": []
      }
    },
    {
      "DownstreamPathTemplate": "/StarratingApi/api/Starrating/GetFYList",
      "DownstreamScheme": "http",
      "DownstreamHostAndPorts": [
        {
          "Host": "localhost",
          "Port": "80"
        }
      ],
      "UpstreamPathTemplate": "/api/Starrating/GetFYList",
      "UpstreamHttpMethod": [ "POST" ],
      "AuthenticationOptions": {
        "AuthenticationProviderKey": "TestKey",
        "AllowedScopes": []
      }
    },
    {
      "DownstreamPathTemplate": "/StarratingApi/api/Starrating/GetMineralList",
      "DownstreamScheme": "http",
      "DownstreamHostAndPorts": [
        {
          "Host": "localhost",
          "Port": "80"
        }
      ],
      "UpstreamPathTemplate": "/api/Starrating/GetMineralList",
      "UpstreamHttpMethod": [ "POST" ],
      "AuthenticationOptions": {
        "AuthenticationProviderKey": "TestKey",
        "AllowedScopes": []
      }
    },
    {
      "DownstreamPathTemplate": "/StarratingApi/api/Starrating/GetLeaseAreaType",
      "DownstreamScheme": "http",
      "DownstreamHostAndPorts": [
        {
          "Host": "localhost",
          "Port": "80"
        }
      ],
      "UpstreamPathTemplate": "/api/Starrating/GetLeaseAreaType",
      "UpstreamHttpMethod": [ "POST" ],
      "AuthenticationOptions": {
        "AuthenticationProviderKey": "TestKey",
        "AllowedScopes": []
      }
    },
    {
      "DownstreamPathTemplate": "/StarratingApi/api/Starrating/GetAssessmentCount",
      "DownstreamScheme": "http",
      "DownstreamHostAndPorts": [
        {
          "Host": "localhost",
          "Port": "80"
        }
      ],
      "UpstreamPathTemplate": "/api/Starrating/GetAssessmentCount",
      "UpstreamHttpMethod": [ "POST" ],
      "AuthenticationOptions": {
        "AuthenticationProviderKey": "TestKey",
        "AllowedScopes": []
      }
    },
    {
      "DownstreamPathTemplate": "/StarratingApi/api/Starrating/GetUserMaster",
      "DownstreamScheme": "http",
      "DownstreamHostAndPorts": [
        {
          "Host": "localhost",
          "Port": "80"
        }
      ],
      "UpstreamPathTemplate": "/api/Starrating/GetUserMaster",
      "UpstreamHttpMethod": [ "POST" ],
      "AuthenticationOptions": {
        "AuthenticationProviderKey": "TestKey",
        "AllowedScopes": []
      }
    },
    {
      "DownstreamPathTemplate": "/StarratingApi/api/Starrating/GetTehsilVillage",
      "DownstreamScheme": "http",
      "DownstreamHostAndPorts": [
        {
          "Host": "localhost",
          "Port": "80"
        }
      ],
      "UpstreamPathTemplate": "/api/Starrating/GetTehsilVillage",
      "UpstreamHttpMethod": [ "POST" ],
      "AuthenticationOptions": {
        "AuthenticationProviderKey": "TestKey",
        "AllowedScopes": []
      }
    },
    {
      "DownstreamPathTemplate": "/StarratingApi/api/Starrating/GetMineralId",
      "DownstreamScheme": "http",
      "DownstreamHostAndPorts": [
        {
          "Host": "localhost",
          "Port": "80"
        }
      ],
      "UpstreamPathTemplate": "/api/Starrating/GetMineralId",
      "UpstreamHttpMethod": [ "POST" ],
      "AuthenticationOptions": {
        "AuthenticationProviderKey": "TestKey",
        "AllowedScopes": []
      }
    },
    {
      "DownstreamPathTemplate": "/StarratingApi/api/Starrating/GetLeasePeriod",
      "DownstreamScheme": "http",
      "DownstreamHostAndPorts": [
        {
          "Host": "localhost",
          "Port": "80"
        }
      ],
      "UpstreamPathTemplate": "/api/Starrating/GetLeasePeriod",
      "UpstreamHttpMethod": [ "POST" ],
      "AuthenticationOptions": {
        "AuthenticationProviderKey": "TestKey",
        "AllowedScopes": []
      }
    },
    {
      "DownstreamPathTemplate": "/StarratingApi/api/Starrating/GetApprovedPlan",
      "DownstreamScheme": "http",
      "DownstreamHostAndPorts": [
        {
          "Host": "localhost",
          "Port": "80"
        }
      ],
      "UpstreamPathTemplate": "/api/Starrating/GetApprovedPlan",
      "UpstreamHttpMethod": [ "POST" ],
      "AuthenticationOptions": {
        "AuthenticationProviderKey": "TestKey",
        "AllowedScopes": []
      }
    },
    {
      "DownstreamPathTemplate": "/StarratingApi/api/Starrating/GetEnvironmentClearanceValidity",
      "DownstreamScheme": "http",
      "DownstreamHostAndPorts": [
        {
          "Host": "localhost",
          "Port": "80"
        }
      ],
      "UpstreamPathTemplate": "/api/Starrating/GetEnvironmentClearanceValidity",
      "UpstreamHttpMethod": [ "POST" ],
      "AuthenticationOptions": {
        "AuthenticationProviderKey": "TestKey",
        "AllowedScopes": []
      }
    },
    {
      "DownstreamPathTemplate": "/StarratingApi/api/Starrating/GetForestClearanceValidityUpto",
      "DownstreamScheme": "http",
      "DownstreamHostAndPorts": [
        {
          "Host": "localhost",
          "Port": "80"
        }
      ],
      "UpstreamPathTemplate": "/api/Starrating/GetForestClearanceValidityUpto",
      "UpstreamHttpMethod": [ "POST" ],
      "AuthenticationOptions": {
        "AuthenticationProviderKey": "TestKey",
        "AllowedScopes": []
      }
    },
    {
      "DownstreamPathTemplate": "/StarratingApi/api/Starrating/Add",
      "DownstreamScheme": "http",
      "DownstreamHostAndPorts": [
        {
          "Host": "localhost",
          "Port": "80"
        }
      ],
      "UpstreamPathTemplate": "/api/Starrating/Add",
      "UpstreamHttpMethod": [ "POST" ],
      "AuthenticationOptions": {
        "AuthenticationProviderKey": "TestKey",
        "AllowedScopes": []
      }
    },
    {
      "DownstreamPathTemplate": "/StarratingApi/api/Starrating/FileUpload",
      "DownstreamScheme": "http",
      "DownstreamHostAndPorts": [
        {
          "Host": "localhost",
          "Port": "80"
        }
      ],
      "UpstreamPathTemplate": "/api/Starrating/FileUpload",
      "UpstreamHttpMethod": [ "POST" ],
      "AuthenticationOptions": {
        "AuthenticationProviderKey": "TestKey",
        "AllowedScopes": []
      }
    },
    {
      "DownstreamPathTemplate": "/StarratingApi/api/Starrating/AddSystSust",
      "DownstreamScheme": "http",
      "DownstreamHostAndPorts": [
        {
          "Host": "localhost",
          "Port": "80"
        }
      ],
      "UpstreamPathTemplate": "/api/Starrating/AddSystSust",
      "UpstreamHttpMethod": [ "POST" ],
      "AuthenticationOptions": {
        "AuthenticationProviderKey": "TestKey",
        "AllowedScopes": []
      }
    },
    {
      "DownstreamPathTemplate": "/StarratingApi/api/Starrating/AddPE",
      "DownstreamScheme": "http",
      "DownstreamHostAndPorts": [
        {
          "Host": "localhost",
          "Port": "80"
        }
      ],
      "UpstreamPathTemplate": "/api/Starrating/AddPE",
      "UpstreamHttpMethod": [ "POST" ],
      "AuthenticationOptions": {
        "AuthenticationProviderKey": "TestKey",
        "AllowedScopes": []
      }
    },
    {
      "DownstreamPathTemplate": "/StarratingApi/api/Starrating/AddHS",
      "DownstreamScheme": "http",
      "DownstreamHostAndPorts": [
        {
          "Host": "localhost",
          "Port": "80"
        }
      ],
      "UpstreamPathTemplate": "/api/Starrating/AddHS",
      "UpstreamHttpMethod": [ "POST" ],
      "AuthenticationOptions": {
        "AuthenticationProviderKey": "TestKey",
        "AllowedScopes": []
      }
    },
    {
      "DownstreamPathTemplate": "/StarratingApi/api/Starrating/AddSC",
      "DownstreamScheme": "http",
      "DownstreamHostAndPorts": [
        {
          "Host": "localhost",
          "Port": "80"
        }
      ],
      "UpstreamPathTemplate": "/api/Starrating/AddSC",
      "UpstreamHttpMethod": [ "POST" ],
      "AuthenticationOptions": {
        "AuthenticationProviderKey": "TestKey",
        "AllowedScopes": []
      }
    },
    {
      "DownstreamPathTemplate": "/StarratingApi/api/Starrating/AddMore",
      "DownstreamScheme": "http",
      "DownstreamHostAndPorts": [
        {
          "Host": "localhost",
          "Port": "80"
        }
      ],
      "UpstreamPathTemplate": "/api/Starrating/AddMore",
      "UpstreamHttpMethod": [ "POST" ],
      "AuthenticationOptions": {
        "AuthenticationProviderKey": "TestKey",
        "AllowedScopes": []
      }
    },
    {
      "DownstreamPathTemplate": "/StarratingApi/api/Starrating/Edit",
      "DownstreamScheme": "http",
      "DownstreamHostAndPorts": [
        {
          "Host": "localhost",
          "Port": "80"
        }
      ],
      "UpstreamPathTemplate": "/api/Starrating/Edit",
      "UpstreamHttpMethod": [ "POST" ],
      "AuthenticationOptions": {
        "AuthenticationProviderKey": "TestKey",
        "AllowedScopes": []
      }
    },
    {
      "DownstreamPathTemplate": "/StarratingApi/api/Starrating/EditLesseePE",
      "DownstreamScheme": "http",
      "DownstreamHostAndPorts": [
        {
          "Host": "localhost",
          "Port": "80"
        }
      ],
      "UpstreamPathTemplate": "/api/Starrating/EditLesseePE",
      "UpstreamHttpMethod": [ "POST" ],
      "AuthenticationOptions": {
        "AuthenticationProviderKey": "TestKey",
        "AllowedScopes": []
      }
    },
    {
      "DownstreamPathTemplate": "/StarratingApi/api/Starrating/EditLesseeSS",
      "DownstreamScheme": "http",
      "DownstreamHostAndPorts": [
        {
          "Host": "localhost",
          "Port": "80"
        }
      ],
      "UpstreamPathTemplate": "/api/Starrating/EditLesseeSS",
      "UpstreamHttpMethod": [ "POST" ],
      "AuthenticationOptions": {
        "AuthenticationProviderKey": "TestKey",
        "AllowedScopes": []
      }
    },
    {
      "DownstreamPathTemplate": "/StarratingApi/api/Starrating/EditLesseeHS",
      "DownstreamScheme": "http",
      "DownstreamHostAndPorts": [
        {
          "Host": "localhost",
          "Port": "80"
        }
      ],
      "UpstreamPathTemplate": "/api/Starrating/EditLesseeHS",
      "UpstreamHttpMethod": [ "POST" ],
      "AuthenticationOptions": {
        "AuthenticationProviderKey": "TestKey",
        "AllowedScopes": []
      }
    },
    {
      "DownstreamPathTemplate": "/StarratingApi/api/Starrating/EditLesseeSC",
      "DownstreamScheme": "http",
      "DownstreamHostAndPorts": [
        {
          "Host": "localhost",
          "Port": "80"
        }
      ],
      "UpstreamPathTemplate": "/api/Starrating/EditLesseeSC",
      "UpstreamHttpMethod": [ "POST" ],
      "AuthenticationOptions": {
        "AuthenticationProviderKey": "TestKey",
        "AllowedScopes": []
      }
    },
    {
      "DownstreamPathTemplate": "/StarratingApi/api/Starrating/GetOtherFiles",
      "DownstreamScheme": "http",
      "DownstreamHostAndPorts": [
        {
          "Host": "localhost",
          "Port": "80"
        }
      ],
      "UpstreamPathTemplate": "/api/Starrating/GetOtherFiles",
      "UpstreamHttpMethod": [ "POST" ],
      "AuthenticationOptions": {
        "AuthenticationProviderKey": "TestKey",
        "AllowedScopes": []
      }
    },
    {
      "DownstreamPathTemplate": "/StarratingApi/api/Starrating/GetInfoFiles",
      "DownstreamScheme": "http",
      "DownstreamHostAndPorts": [
        {
          "Host": "localhost",
          "Port": "80"
        }
      ],
      "UpstreamPathTemplate": "/api/Starrating/GetInfoFiles",
      "UpstreamHttpMethod": [ "POST" ],
      "AuthenticationOptions": {
        "AuthenticationProviderKey": "TestKey",
        "AllowedScopes": []
      }
    },
    {
      "DownstreamPathTemplate": "/StarratingApi/api/Starrating/GetCoordinateList",
      "DownstreamScheme": "http",
      "DownstreamHostAndPorts": [
        {
          "Host": "localhost",
          "Port": "80"
        }
      ],
      "UpstreamPathTemplate": "/api/Starrating/GetCoordinateList",
      "UpstreamHttpMethod": [ "POST" ],
      "AuthenticationOptions": {
        "AuthenticationProviderKey": "TestKey",
        "AllowedScopes": []
      }
    },
    {
      "DownstreamPathTemplate": "/StarratingApi/api/Starrating/GetLeaseAreaList",
      "DownstreamScheme": "http",
      "DownstreamHostAndPorts": [
        {
          "Host": "localhost",
          "Port": "80"
        }
      ],
      "UpstreamPathTemplate": "/api/Starrating/GetLeaseAreaList",
      "UpstreamHttpMethod": [ "POST" ],
      "AuthenticationOptions": {
        "AuthenticationProviderKey": "TestKey",
        "AllowedScopes": []
      }
    },
    {
      "DownstreamPathTemplate": "/StarratingApi/api/Starrating/GetLeaseTypeList",
      "DownstreamScheme": "http",
      "DownstreamHostAndPorts": [
        {
          "Host": "localhost",
          "Port": "80"
        }
      ],
      "UpstreamPathTemplate": "/api/Starrating/GetLeaseTypeList",
      "UpstreamHttpMethod": [ "POST" ],
      "AuthenticationOptions": {
        "AuthenticationProviderKey": "TestKey",
        "AllowedScopes": []
      }
    },
    /*********************For Exception Data******************************/
    {
      "DownstreamPathTemplate": "/StarratingApi/api/ExceptionData/AddException",
      "DownstreamScheme": "http",
      "DownstreamHostAndPorts": [
        {
          "Host": "localhost",
          "Port": "80"
        }
      ],
      "UpstreamPathTemplate": "/api/ExceptionData/AddException",
      "UpstreamHttpMethod": [ "POST" ],
      "AuthenticationOptions": {
        "AuthenticationProviderKey": "TestKey",
        "AllowedScopes": []
      }
    },
    {
      "DownstreamPathTemplate": "/StarratingApi/api/ExceptionData/getuserDetail",
      "DownstreamScheme": "http",
      "DownstreamHostAndPorts": [
        {
          "Host": "localhost",
          "Port": "80"
        }
      ],
      "UpstreamPathTemplate": "/api/ExceptionData/getuserDetail",
      "UpstreamHttpMethod": [ "POST" ],
      "AuthenticationOptions": {
        "AuthenticationProviderKey": "TestKey",
        "AllowedScopes": []
      }
    },
    {
      "DownstreamPathTemplate": "/StarratingApi/api/ExceptionData/MenuList",
      "DownstreamScheme": "http",
      "DownstreamHostAndPorts": [
        {
          "Host": "localhost",
          "Port": "80"
        }
      ],
      "UpstreamPathTemplate": "/api/ExceptionData/MenuList",
      "UpstreamHttpMethod": [ "POST" ],
      "AuthenticationOptions": {
        "AuthenticationProviderKey": "TestKey",
        "AllowedScopes": []
      }
    },
    {
      "DownstreamPathTemplate": "/StarratingApi/api/ExceptionData/AddApiException",
      "DownstreamScheme": "http",
      "DownstreamHostAndPorts": [
        {
          "Host": "localhost",
          "Port": "80"
        }
      ],
      "UpstreamPathTemplate": "/api/ExceptionData/AddApiException",
      "UpstreamHttpMethod": [ "POST" ],
      "AuthenticationOptions": {
        "AuthenticationProviderKey": "TestKey",
        "AllowedScopes": []
      }
    },
    /*********************************************************************/
    {
      "DownstreamPathTemplate": "/AuthServer/api/auth",
      "DownstreamScheme": "http",
      "DownstreamHostAndPorts": [
        {
          "Host": "localhost",
         "Port": "80"
        }
      ],
      "UpstreamPathTemplate": "/api/auth",
      "UpstreamHttpMethod": [ "Get" ]
    }
  ]
}